object_condensation/__init__.py
object_condensation/_version.py
object_condensation/_version.pyi
object_condensation/py.typed
object_condensation/pytorch/__init__.py
object_condensation/pytorch/losses.py
object_condensation/tensorflow/__init__.py
object_condensation/tensorflow/losses.py
object_condensation-1.1.0.dist-info/METADATA
object_condensation-1.1.0.dist-info/WHEEL
object_condensation-1.1.0.dist-info/licenses/LICENSE
object_condensation-1.1.0.dist-info/RECORD
