Metadata-Version: 2.1
Name: object_condensation
Version: 1.1.0
Summary: Efficient implementations of the Object Condensation losses (Jan Kieseler, 2020)
Project-URL: Homepage, https://github.com/object-condensation/object_condensation
Project-URL: Bug Tracker, https://github.com/object-condensation/object_condensation/issues
Project-URL: Discussions, https://github.com/object-condensation/object_condensation/discussions
Project-URL: Changelog, https://github.com/object-condensation/object_condensation/releases
Author-email: Kilian Lieret <kilian.lieret@posteo.de>, Philipp Zehetner <philipp.zehetner@cern.ch>
License-File: LICENSE
Classifier: Development Status :: 1 - Planning
Classifier: Intended Audience :: Developers
Classifier: Intended Audience :: Science/Research
Classifier: License :: OSI Approved :: MIT License
Classifier: Operating System :: OS Independent
Classifier: Programming Language :: Python
Classifier: Programming Language :: Python :: 3
Classifier: Programming Language :: Python :: 3 :: Only
Classifier: Programming Language :: Python :: 3.8
Classifier: Programming Language :: Python :: 3.9
Classifier: Programming Language :: Python :: 3.10
Classifier: Programming Language :: Python :: 3.11
Classifier: Programming Language :: Python :: 3.12
Classifier: Topic :: Scientific/Engineering
Classifier: Typing :: Typed
Requires-Python: >=3.8
Provides-Extra: dev
Requires-Dist: pytest-cov>=3; extra == 'dev'
Requires-Dist: pytest>=6; extra == 'dev'
Provides-Extra: docs
Requires-Dist: furo>=2023.08.17; extra == 'docs'
Requires-Dist: myst-parser>=0.13; extra == 'docs'
Requires-Dist: sphinx-autodoc-typehints; extra == 'docs'
Requires-Dist: sphinx-copybutton; extra == 'docs'
Requires-Dist: sphinx>=7.0; extra == 'docs'
Provides-Extra: pytorch
Requires-Dist: torch>=1.0; extra == 'pytorch'
Provides-Extra: tensorflow
Requires-Dist: tensorflow>=2.0; extra == 'tensorflow'
Provides-Extra: test
Requires-Dist: pytest-cov>=3; extra == 'test'
Requires-Dist: pytest>=6; extra == 'test'
